{"users":{"poppp":{"userID":"poppp","password":"dsds","type":"instructor","classCode":"y16u2f","totalPoints":0,"previousTotalPoints":0,"highestLevelReached":0,"currentCheckpoint":0,"checkpointX":0,"checkpointY":0},"dsds":{"userID":"dsds","password":"sds","type":"student","classCode":"y16u2f","totalPoints":0,"previousTotalPoints":0,"highestLevelReached":0,"currentCheckpoint":0,"checkpointX":0,"checkpointY":0},"dev":{"userID":"dev","password":"FAAJS","type":"developer","totalPoints":0,"previousTotalPoints":0,"highestLevelReached":0,"currentCheckpoint":0,"checkpointX":0,"checkpointY":0},"test1":{"userID":"test1","password":"test1","type":"student","classCode":"y16u2f","totalPoints":0,"previousTotalPoints":0,"highestLevelReached":0,"currentCheckpoint":0,"checkpointX":0,"checkpointY":0},"fran":{"userID":"fran","password":"marq","type":"student","classCode":"y16u2f","totalPoints":0,"previousTotalPoints":0,"highestLevelReached":0,"currentCheckpoint":0,"checkpointX":0,"checkpointY":0},"werw":{"userID":"werw","password":"Enter Password","type":"instructor","classCode":"m11y8y","totalPoints":0,"previousTotalPoints":0,"highestLevelReached":0,"currentCheckpoint":0,"checkpointX":0,"checkpointY":0},"instructor3":{"userID":"instructor3","password":"werrr","type":"instructor","classCode":"b9n0x5","totalPoints":0,"previousTotalPoints":0,"highestLevelReached":0,"currentCheckpoint":0,"checkpointX":0,"checkpointY":0},"aaaaaa":{"userID":"aaaaaa","password":"werrr","type":"instructor","classCode":"z7332b","totalPoints":0,"previousTotalPoints":0,"highestLevelReached":0,"currentCheckpoint":0,"checkpointX":0,"checkpointY":0},"umm":{"userID":"umm","password":"hahahaha","type":"instructor","classCode":"h78s4v","totalPoints":0,"previousTotalPoints":0,"highestLevelReached":0,"currentCheckpoint":0,"checkpointX":0,"checkpointY":0},"tyuii":{"userID":"tyuii","password":"hahahaha","type":"instructor","classCode":"p57a0a","totalPoints":0,"previousTotalPoints":0,"highestLevelReached":0,"currentCheckpoint":0,"checkpointX":0,"checkpointY":0}}}